{
  "type": "FeatureCollection",
  "features": [
    {
      "type": "Feature",
      "properties": {
        "name": "Parish of St. John the Baptist (Wrocław)",
        "deanery": "Wrocław Central",
        "diocese": "Archdiocese of Wrocław",
        "records": [
          {
            "type": "Births",
            "periods": [
              { "from": 1780, "to": 1820, "url": "https://example.com/a" },
              { "from": 1830, "to": 1870, "url": "https://example.com/b" }
            ]
          },
          {
            "type": "Marriages",
            "periods": [
              { "from": 1760, "to": 1820, "url": "https://example.com/a" },
              { "from": 1830, "to": 1840, "url": "https://example.com/b" }
            ]
          },
          {
            "type": "Deaths",
            "periods": [
              { "from": 1780, "to": 1820, "url": "https://example.com/a" },
              { "from": 1830, "to": 1870, "url": "https://example.com/b" }
            ]
          }
        ]
      },
      "geometry": {
        "type": "Point",
        "coordinates": [17.0385, 51.1079]
      }
    },
    {
      "type": "Feature",
      "properties": {
        "name": "Parish of St. Hedwig (Trzebnica)",
        "deanery": "Trzebnica",
        "diocese": "Archdiocese of Wrocław",
        "records": [
          {
            "type": "Births",
            "periods": [
              { "from": 1780, "to": 1820, "url": "https://example.com/a" },
              { "from": 1830, "to": 1870, "url": "https://example.com/b" }
            ]
          },
          {
            "type": "Marriages",
            "periods": [
              { "from": 1780, "to": 1820, "url": "https://example.com/a" },
              { "from": 1830, "to": 1870, "url": "https://example.com/b" }
            ]
          }
        ]
      },
      "geometry": {
        "type": "Point",
        "coordinates": [17.0631, 51.3104]
      }
    }
  ]
}
